keras2trt/__init__.py
keras2trt/cli.py
keras2trt/enums.py
keras2trt/logging.py
keras2trt/model_converter.py
keras2trt/version.py
keras2trt-0.5.0.dist-info/METADATA
keras2trt-0.5.0.dist-info/WHEEL
keras2trt-0.5.0.dist-info/entry_points.txt
keras2trt-0.5.0.dist-info/RECORD
