Metadata-Version: 2.1
Name: keras2trt
Version: 0.5.0
Summary: CLI to convert TensorFlow models to TensorRT engines
Home-page: https://pypi.org/project/keras2trt/
License: MIT
Author: Emrecan Altinsoy
Author-email: emrecanaltinsoy@gmail.com
Requires-Python: >=3.8,<3.11
Classifier: License :: OSI Approved :: MIT License
Classifier: Programming Language :: Python :: 3
Classifier: Programming Language :: Python :: 3.8
Classifier: Programming Language :: Python :: 3.9
Classifier: Programming Language :: Python :: 3.10
Requires-Dist: onnx (==1.10.2)
Requires-Dist: protobuf (>=3.9.2,<3.20)
Requires-Dist: tensorflow (>=2.8.0)
Requires-Dist: tf2onnx (==1.12.1)
Requires-Dist: tomlkit (>=0.11.4,<0.12.0)
Requires-Dist: typer (==0.6.1)
Project-URL: Repository, https://github.com/emrecanaltinsoy/keras2trt
